dji_telemetry/__init__.py
dji_telemetry/exporter.py
dji_telemetry/overlay.py
dji_telemetry/parser.py
dji_telemetry/video.py
dji_telemetry-1.0.0.dist-info/licenses/LICENSE
dji_telemetry-1.0.0.dist-info/METADATA
dji_telemetry-1.0.0.dist-info/WHEEL
dji_telemetry-1.0.0.dist-info/entry_points.txt
dji_telemetry-1.0.0.dist-info/top_level.txt
dji_telemetry-1.0.0.dist-info/RECORD
