Metadata-Version: 2.4
Name: dji-telemetry
Version: 1.0.0
Summary: Parse DJI drone SRT telemetry files and overlay flight data onto video footage
Author: jetervaz
License: MIT
Project-URL: Homepage, https://github.com/jetervaz/dji-telemetry
Project-URL: Repository, https://github.com/jetervaz/dji-telemetry
Project-URL: Issues, https://github.com/jetervaz/dji-telemetry/issues
Keywords: dji,drone,telemetry,video,overlay,gpx,srt
Classifier: Development Status :: 4 - Beta
Classifier: Intended Audience :: Developers
Classifier: Intended Audience :: End Users/Desktop
Classifier: License :: OSI Approved :: MIT License
Classifier: Operating System :: OS Independent
Classifier: Programming Language :: Python :: 3
Classifier: Programming Language :: Python :: 3.8
Classifier: Programming Language :: Python :: 3.9
Classifier: Programming Language :: Python :: 3.10
Classifier: Programming Language :: Python :: 3.11
Classifier: Programming Language :: Python :: 3.12
Classifier: Topic :: Multimedia :: Video
Classifier: Topic :: Scientific/Engineering :: GIS
Requires-Python: >=3.8
License-File: LICENSE
Requires-Dist: opencv-python>=4.5.0
Requires-Dist: numpy>=1.19.0
Provides-Extra: dev
Requires-Dist: pytest>=7.0; extra == "dev"
Requires-Dist: pytest-cov; extra == "dev"
Dynamic: license-file
